<?xml version="1.0" encoding="UTF-8"?>
<objects serializationModel="Studio.02.02.00">
	<object class="AudioFile" id="{4b3a96bc-8e9e-407f-9c30-34da5f8c0a82}">
		<property name="assetPath">
			<value>Misc/GeeArtriasRose_-_Hapi_Drum_Duet.mp3</value>
		</property>
		<property name="isStreaming">
			<value>true</value>
		</property>
		<property name="frequencyInKHz">
			<value>48</value>
		</property>
		<property name="channelCount">
			<value>2</value>
		</property>
		<property name="length">
			<value>90.048000000000002</value>
		</property>
		<relationship name="masterAssetFolder">
			<destination>{f930ae7e-03ac-4797-acd5-e828f088234b}</destination>
		</relationship>
	</object>
</objects>
